{
    "subclass_of": [
        "Category:OSWafcac83979f4472298b6acdc01981728"
    ],
    "type": [
        "Category:Category"
    ],
    "uuid": "a2c8dd38-7d0b-4a0c-807a-5a7bde190ba3",
    "label": [
        {
            "text": "Standard Operating Procedure",
            "lang": "en"
        },
        {
            "text": "Standard Operation Procedure",
            "lang": "en"
        },
        {
            "text": "Standard Operating Procedure",
            "lang": "de"
        },
        {
            "text": "Standardvorgehensweise",
            "lang": "de"
        },
        {
            "text": "standardisiertes Vorgehen",
            "lang": "de"
        },
        {
            "text": "Standardarbeitsanweisung",
            "lang": "de"
        }
    ],
    "short_name": [
        {
            "text": "SOP",
            "lang": "en"
        },
        {
            "text": "SOP",
            "lang": "de"
        }
    ],
    "description": [
        {
            "text": "A standard operating procedure (SOP) is a set of step-by-step instructions compiled by an organization to help workers carry out routine operations. SOPs aim to achieve efficiency, quality output, and uniformity of performance, while reducing miscommunication and failure to comply with industry regulations.",
            "lang": "en"
        },
        {
            "text": "Eine Standardarbeitsanweisung (SOP) ist eine Reihe von Schritt-für-Schritt-Anweisungen, die von einer Organisation zusammengestellt werden, um den Mitarbeitern bei der Durchführung von Routinearbeiten zu helfen[1].",
            "lang": "de"
        }
    ],
    "name": "StandardOperatingProcedure"
}